candlestick/__init__.py
candlestick/models.py
candlestick/utils.py
candlestick/yahoo.py
candlestick/management/__init__.py
candlestick/management/commands/__init__.py
candlestick/management/commands/fetch.py
candlestick/management/commands/update.py
candlestick/migrations/0001_initial.py
candlestick/migrations/__init__.py
django_candlestick-0.2.0.dist-info/LICENSE
django_candlestick-0.2.0.dist-info/METADATA
django_candlestick-0.2.0.dist-info/WHEEL
django_candlestick-0.2.0.dist-info/top_level.txt
django_candlestick-0.2.0.dist-info/RECORD
